openai_api_key_verifier/__init__.py
openai_api_key_verifier/verify_api_key.py
openai_api_key_verifier-1.0.2.dist-info/LICENSE
openai_api_key_verifier-1.0.2.dist-info/METADATA
openai_api_key_verifier-1.0.2.dist-info/WHEEL
openai_api_key_verifier-1.0.2.dist-info/entry_points.txt
openai_api_key_verifier-1.0.2.dist-info/top_level.txt
openai_api_key_verifier-1.0.2.dist-info/RECORD
