Metadata-Version: 2.1
Name: openai_api_key_verifier
Version: 1.0.2
Summary: A Python library for validating OpenAI API keys, and listing available models and verifying model access, and retrieving detailed account usage metrics.
Home-page: https://github.com/mdeacey/openai-api-key-verifier/
Author: Marcus Deacey
Author-email: marcusdeacey@duck.com
Classifier: Programming Language :: Python :: 3
Classifier: License :: OSI Approved :: MIT License
Classifier: Operating System :: OS Independent
Requires-Python: >=3.6
License-File: LICENSE
